prayerpy/__init__.py
prayerpy/config.py
prayerpy/degree_geometry.py
prayerpy/equation_of_time.py
prayerpy/main.py
prayerpy/prayer_time.py
prayerpy/sun_declination.py
prayerpy-0.1.dist-info/METADATA
prayerpy-0.1.dist-info/WHEEL
prayerpy-0.1.dist-info/top_level.txt
prayerpy-0.1.dist-info/RECORD
