Metadata-Version: 2.2
Name: prayerpy
Version: 0.1
Author: Galalem
License: GPL 3.0
Dynamic: author
Dynamic: description
Dynamic: description-content-type
Dynamic: license
